<?xml version="1.0" encoding="UTF-8"?>
<MetaDataObject xmlns="http://v8.1c.ru/8.3/MDClasses" xmlns:app="http://v8.1c.ru/8.2/managed-application/core" xmlns:cfg="http://v8.1c.ru/8.1/data/enterprise/current-config" xmlns:cmi="http://v8.1c.ru/8.2/managed-application/cmi" xmlns:ent="http://v8.1c.ru/8.1/data/enterprise" xmlns:lf="http://v8.1c.ru/8.2/managed-application/logform" xmlns:style="http://v8.1c.ru/8.1/data/ui/style" xmlns:sys="http://v8.1c.ru/8.1/data/ui/fonts/system" xmlns:v8="http://v8.1c.ru/8.1/data/core" xmlns:v8ui="http://v8.1c.ru/8.1/data/ui" xmlns:web="http://v8.1c.ru/8.1/data/ui/colors/web" xmlns:win="http://v8.1c.ru/8.1/data/ui/colors/windows" xmlns:xen="http://v8.1c.ru/8.3/xcf/enums" xmlns:xpr="http://v8.1c.ru/8.3/xcf/predef" xmlns:xr="http://v8.1c.ru/8.3/xcf/readable" xmlns:xs="http://www.w3.org/2001/XMLSchema" xmlns:xsi="http://www.w3.org/2001/XMLSchema-instance" version="2.18">
	<CalculationRegister uuid="a1bfa06c-9c35-494b-8070-44a7a91ad7a0">
		<InternalInfo>
			<xr:GeneratedType name="CalculationRegisterRecord.ДопНачисления" category="Record">
				<xr:TypeId>c08bd2e8-4411-4340-ad9d-fb66dfd6f4a4</xr:TypeId>
				<xr:ValueId>577b944a-3eab-487a-b7de-5916b7ec7202</xr:ValueId>
			</xr:GeneratedType>
			<xr:GeneratedType name="CalculationRegisterManager.ДопНачисления" category="Manager">
				<xr:TypeId>b60f7ac2-e73f-4762-aacb-4deed68f4059</xr:TypeId>
				<xr:ValueId>88142b2e-5b4c-4265-869e-b606042c7de5</xr:ValueId>
			</xr:GeneratedType>
			<xr:GeneratedType name="CalculationRegisterSelection.ДопНачисления" category="Selection">
				<xr:TypeId>1c0ababf-79af-473c-a69c-8b5a867b52ae</xr:TypeId>
				<xr:ValueId>e62d2fbe-7feb-47dd-897b-76e64babb00f</xr:ValueId>
			</xr:GeneratedType>
			<xr:GeneratedType name="CalculationRegisterList.ДопНачисления" category="List">
				<xr:TypeId>f6e78641-c904-43d6-893a-e82ac0a62ab1</xr:TypeId>
				<xr:ValueId>3fc1f5a4-a6e1-4010-bb79-26da8e9cabf8</xr:ValueId>
			</xr:GeneratedType>
			<xr:GeneratedType name="CalculationRegisterRecordSet.ДопНачисления" category="RecordSet">
				<xr:TypeId>ad574249-df2d-410a-8c2b-d74c9951d7d4</xr:TypeId>
				<xr:ValueId>5e7ec78b-b9a1-4d7c-b9f5-679f129cf87a</xr:ValueId>
			</xr:GeneratedType>
			<xr:GeneratedType name="CalculationRegisterRecordKey.ДопНачисления" category="RecordKey">
				<xr:TypeId>23f508da-b946-44f4-adf9-cb4e1b9a79f1</xr:TypeId>
				<xr:ValueId>1b480dd1-99db-4e69-8263-197c782d6657</xr:ValueId>
			</xr:GeneratedType>
			<xr:GeneratedType name="RecalculationsManager.ДопНачисления" category="Recalcs">
				<xr:TypeId>502daf10-3169-4295-a3fe-00e037cc18c6</xr:TypeId>
				<xr:ValueId>0b7b750c-0d3f-407a-b3f3-4bed4fb93519</xr:ValueId>
			</xr:GeneratedType>
		</InternalInfo>
		<Properties>
			<Name>ДопНачисления</Name>
			<Synonym>
				<v8:item>
					<v8:lang>ru</v8:lang>
					<v8:content>Доп начисления</v8:content>
				</v8:item>
			</Synonym>
			<Comment/>
			<UseStandardCommands>true</UseStandardCommands>
			<DefaultListForm/>
			<AuxiliaryListForm/>
			<Periodicity>Month</Periodicity>
			<ActionPeriod>false</ActionPeriod>
			<BasePeriod>true</BasePeriod>
			<Schedule/>
			<ScheduleValue/>
			<ScheduleDate/>
			<ChartOfCalculationTypes>ChartOfCalculationTypes.ДопНачисления</ChartOfCalculationTypes>
			<IncludeHelpInContents>false</IncludeHelpInContents>
			<DataLockControlMode>Managed</DataLockControlMode>
			<FullTextSearch>DontUse</FullTextSearch>
			<ListPresentation/>
			<ExtendedListPresentation/>
			<Explanation/>
		</Properties>
		<ChildObjects>
			<Resource uuid="f69b05a4-a4db-42ad-a3ee-019011fab279">
				<Properties>
					<Name>Результат</Name>
					<Synonym>
						<v8:item>
							<v8:lang>ru</v8:lang>
							<v8:content>Результат</v8:content>
						</v8:item>
					</Synonym>
					<Comment/>
					<Type>
						<v8:Type>xs:decimal</v8:Type>
						<v8:NumberQualifiers>
							<v8:Digits>10</v8:Digits>
							<v8:FractionDigits>2</v8:FractionDigits>
							<v8:AllowedSign>Nonnegative</v8:AllowedSign>
						</v8:NumberQualifiers>
					</Type>
					<PasswordMode>false</PasswordMode>
					<Format/>
					<EditFormat/>
					<ToolTip/>
					<MarkNegatives>false</MarkNegatives>
					<Mask/>
					<MultiLine>false</MultiLine>
					<ExtendedEdit>false</ExtendedEdit>
					<MinValue xsi:nil="true"/>
					<MaxValue xsi:nil="true"/>
					<FillChecking>DontCheck</FillChecking>
					<ChoiceFoldersAndItems>Items</ChoiceFoldersAndItems>
					<ChoiceParameterLinks/>
					<ChoiceParameters/>
					<QuickChoice>Auto</QuickChoice>
					<CreateOnInput>Auto</CreateOnInput>
					<ChoiceForm/>
					<LinkByType/>
					<ChoiceHistoryOnInput>Auto</ChoiceHistoryOnInput>
					<FullTextSearch>Use</FullTextSearch>
				</Properties>
			</Resource>
			<Attribute uuid="a9ea1537-bda3-4df5-a602-cbef5be7759c">
				<Properties>
					<Name>Стаж</Name>
					<Synonym>
						<v8:item>
							<v8:lang>ru</v8:lang>
							<v8:content>Стаж</v8:content>
						</v8:item>
					</Synonym>
					<Comment/>
					<Type>
						<v8:Type>xs:decimal</v8:Type>
						<v8:NumberQualifiers>
							<v8:Digits>10</v8:Digits>
							<v8:FractionDigits>0</v8:FractionDigits>
							<v8:AllowedSign>Nonnegative</v8:AllowedSign>
						</v8:NumberQualifiers>
					</Type>
					<PasswordMode>false</PasswordMode>
					<Format/>
					<EditFormat/>
					<ToolTip/>
					<MarkNegatives>false</MarkNegatives>
					<Mask/>
					<MultiLine>false</MultiLine>
					<ExtendedEdit>false</ExtendedEdit>
					<MinValue xsi:nil="true"/>
					<MaxValue xsi:nil="true"/>
					<FillChecking>DontCheck</FillChecking>
					<ChoiceFoldersAndItems>Items</ChoiceFoldersAndItems>
					<ChoiceParameterLinks/>
					<ChoiceParameters/>
					<QuickChoice>Auto</QuickChoice>
					<CreateOnInput>Auto</CreateOnInput>
					<ChoiceForm/>
					<LinkByType/>
					<ChoiceHistoryOnInput>Auto</ChoiceHistoryOnInput>
					<ScheduleLink/>
					<Indexing>DontIndex</Indexing>
					<FullTextSearch>Use</FullTextSearch>
				</Properties>
			</Attribute>
			<Attribute uuid="af40ffa7-d7cb-4df5-a1b8-95ae863ddb43">
				<Properties>
					<Name>Параметр</Name>
					<Synonym>
						<v8:item>
							<v8:lang>ru</v8:lang>
							<v8:content>Параметр</v8:content>
						</v8:item>
					</Synonym>
					<Comment/>
					<Type>
						<v8:Type>xs:decimal</v8:Type>
						<v8:NumberQualifiers>
							<v8:Digits>15</v8:Digits>
							<v8:FractionDigits>2</v8:FractionDigits>
							<v8:AllowedSign>Nonnegative</v8:AllowedSign>
						</v8:NumberQualifiers>
					</Type>
					<PasswordMode>false</PasswordMode>
					<Format/>
					<EditFormat/>
					<ToolTip/>
					<MarkNegatives>false</MarkNegatives>
					<Mask/>
					<MultiLine>false</MultiLine>
					<ExtendedEdit>false</ExtendedEdit>
					<MinValue xsi:nil="true"/>
					<MaxValue xsi:nil="true"/>
					<FillChecking>DontCheck</FillChecking>
					<ChoiceFoldersAndItems>Items</ChoiceFoldersAndItems>
					<ChoiceParameterLinks/>
					<ChoiceParameters/>
					<QuickChoice>Auto</QuickChoice>
					<CreateOnInput>Auto</CreateOnInput>
					<ChoiceForm/>
					<LinkByType/>
					<ChoiceHistoryOnInput>Auto</ChoiceHistoryOnInput>
					<ScheduleLink/>
					<Indexing>DontIndex</Indexing>
					<FullTextSearch>Use</FullTextSearch>
				</Properties>
			</Attribute>
			<Dimension uuid="71f23417-2178-4863-ab64-a78cb7ab0f8b">
				<Properties>
					<Name>Сотрудник</Name>
					<Synonym>
						<v8:item>
							<v8:lang>ru</v8:lang>
							<v8:content>Сотрудник</v8:content>
						</v8:item>
					</Synonym>
					<Comment/>
					<Type>
						<v8:Type>cfg:CatalogRef.Сотрудники</v8:Type>
					</Type>
					<PasswordMode>false</PasswordMode>
					<Format/>
					<EditFormat/>
					<ToolTip/>
					<MarkNegatives>false</MarkNegatives>
					<Mask/>
					<MultiLine>false</MultiLine>
					<ExtendedEdit>false</ExtendedEdit>
					<MinValue xsi:nil="true"/>
					<MaxValue xsi:nil="true"/>
					<FillChecking>DontCheck</FillChecking>
					<ChoiceFoldersAndItems>Items</ChoiceFoldersAndItems>
					<ChoiceParameterLinks/>
					<ChoiceParameters/>
					<QuickChoice>Auto</QuickChoice>
					<CreateOnInput>Auto</CreateOnInput>
					<ChoiceForm/>
					<LinkByType/>
					<ChoiceHistoryOnInput>Auto</ChoiceHistoryOnInput>
					<DenyIncompleteValues>false</DenyIncompleteValues>
					<BaseDimension>false</BaseDimension>
					<ScheduleLink/>
					<Indexing>DontIndex</Indexing>
					<FullTextSearch>Use</FullTextSearch>
				</Properties>
			</Dimension>
		</ChildObjects>
	</CalculationRegister>
</MetaDataObject>